pgn_downloader/__init__.py
pgn_downloader/__main__.py
pgn_downloader/chess_com.py
pgn_downloader/date_parser.py
pgn_downloader/lichess.py
pgn_downloader/version.py
pgn_downloader-0.2.2.dist-info/COPYING
pgn_downloader-0.2.2.dist-info/METADATA
pgn_downloader-0.2.2.dist-info/WHEEL
pgn_downloader-0.2.2.dist-info/entry_points.txt
pgn_downloader-0.2.2.dist-info/top_level.txt
pgn_downloader-0.2.2.dist-info/RECORD
