Metadata-Version: 2.1
Name: pgn-downloader
Version: 0.2.2
Summary: Tool to download games from a specific user on Lichess.org or chess.com
Home-page: https://github.com/Simske/pgn-downloader
Author: Simske, Chessdjw
Author-email: mail@simske.com, dejowa97@web.de
Project-URL: Bug Tracker, https://github.com/Simske/pgn-downloader/issues
Classifier: Programming Language :: Python :: 3
Classifier: Operating System :: OS Independent
Classifier: License :: OSI Approved :: GNU General Public License v3 (GPLv3)
Classifier: Development Status :: 4 - Beta
Classifier: Environment :: Console
Classifier: Topic :: Games/Entertainment :: Board Games
Requires-Python: >=3.6
License-File: COPYING
Requires-Dist: requests
Requires-Dist: tqdm
Provides-Extra: dev
Requires-Dist: mypy ; extra == 'dev'
Requires-Dist: types-requests ; extra == 'dev'
